buildbot_phorge/__init__.py
buildbot_phorge/hook.py
buildbot_phorge/reporter.py
buildbot_phorge/utils.py
buildbot_phorge-22.8.0.dist-info/LICENSE
buildbot_phorge-22.8.0.dist-info/METADATA
buildbot_phorge-22.8.0.dist-info/WHEEL
buildbot_phorge-22.8.0.dist-info/entry_points.txt
buildbot_phorge-22.8.0.dist-info/top_level.txt
buildbot_phorge-22.8.0.dist-info/RECORD
