Metadata-Version: 2.1
Name: buildbot-phorge
Version: 22.8.0
Summary: buildbot-phorge integration
Home-page: https://git.sr.ht/~evilham/buildbot-phorge/
Author: Evilham
Author-email: contact@evilham.com
Classifier: Programming Language :: Python :: 3
Classifier: Programming Language :: Python :: 3.9
Classifier: License :: OSI Approved :: BSD License
Classifier: Operating System :: OS Independent
Classifier: Topic :: Software Development :: Build Tools
Classifier: Topic :: Software Development :: Testing
Classifier: Intended Audience :: Developers
Requires-Python: >=3.6
License-File: LICENSE
